ale/__init__.py
ale/encoders.py
ale/rotation.py
ale/transformation.py
ale/util.py
ale/base/__init__.py
ale/base/base.py
ale/base/data_isis.py
ale/base/data_naif.py
ale/base/label_isis.py
ale/base/label_pds3.py
ale/base/type_distortion.py
ale/base/type_sensor.py
ale/drivers/__init__.py
ale/drivers/cassini_drivers.py
ale/drivers/dawn_drivers.py
ale/drivers/isis_ideal_drivers.py
ale/drivers/kaguya_drivers.py
ale/drivers/lro_drivers.py
ale/drivers/messenger_drivers.py
ale/drivers/mex_drivers.py
ale/drivers/mro_drivers.py
ale/formatters/__init__.py
ale/formatters/isis_formatter.py
ale/formatters/usgscsm_formatter.py
Ale-0.2.0.dist-info/LICENSE
Ale-0.2.0.dist-info/METADATA
Ale-0.2.0.dist-info/WHEEL
Ale-0.2.0.dist-info/top_level.txt
Ale-0.2.0.dist-info/RECORD
