Metadata-Version: 2.1
Name: Ale
Version: 0.2.0
Summary: Abstraction Layer for Ephemerides
Home-page: UNKNOWN
Author: UNKNOWN
Author-email: jlaura@usgs.gov
License: UNKNOWN
Platform: UNKNOWN
